atomind_mlip/__init__.py
atomind_mlip-0.0.1.dist-info/WHEEL
atomind_mlip-0.0.1.dist-info/METADATA
atomind_mlip-0.0.1.dist-info/RECORD
