Metadata-Version: 2.1
Name: atomind_mlip
Version: 0.0.1
Summary: 
Keywords: pytorch,machine-learning-interatomic-potentials,huggingface,deep-learning,graph-neural-networks
Author-email: Yuan Chiang <cyrusyc@lbl.gov>
Requires-Python: >=3.8
Classifier: Development Status :: 1 - Planning
Classifier: Programming Language :: Python
Classifier: Programming Language :: Python :: 3.11
Classifier: Programming Language :: Python :: 3.12
Classifier: Programming Language :: Python :: 3 :: Only
Requires-Dist: torch
Project-URL: Homepage, https://github.com/atomind-ai/mlip-arena
Project-URL: Issues, https://github.com/atomind-ai/mlip-arena/issues
